finops_lib/__init__.py
finops_lib/anomaly.py
finops_lib/auth_utils.py
finops_lib/aws.py
finops_lib/azure.py
finops_lib/base.py
finops_lib/cli.py
finops_lib/config.py
finops_lib/forecast.py
finops_lib/gcp.py
finops_lib/optimize.py
finops_lib/recommendations.py
finops_lib/reporting.py
finops_lib/scoring.py
finops_lib/sustainability.py
finops_lib/visualization.py
finops_lib/web.py
finops_lib-1.2.0.dist-info/METADATA
finops_lib-1.2.0.dist-info/WHEEL
finops_lib-1.2.0.dist-info/entry_points.txt
finops_lib-1.2.0.dist-info/top_level.txt
finops_lib-1.2.0.dist-info/RECORD
