Metadata-Version: 2.4
Name: finops_lib
Version: 1.2.0
Summary: Multi-cloud FinOps Python library for cost analysis
Requires-Python: >=3.8
Requires-Dist: boto3
Requires-Dist: azure-mgmt-costmanagement
Requires-Dist: azure-identity
Requires-Dist: google-cloud-bigquery
Requires-Dist: pandas
Requires-Dist: click
Requires-Dist: scikit-learn
Requires-Dist: tabulate
Requires-Dist: reportlab
Requires-Dist: flask>=2.0.0
Requires-Dist: plotly>=5.10.0
Requires-Dist: dash>=2.7.0
Requires-Dist: dash-bootstrap-components>=1.2.0
Requires-Dist: numpy>=1.20.0
Requires-Dist: apscheduler>=3.9.0
